{
  "contract": "AYO-BACKEND-CERTIFICATION-CHECKPOINT-MANIFEST-1",
  "recorded_on": "2026-07-24",
  "base_commit": "85ddc15834d34cd664c728c0560b16964e950d8d",
  "scope": "PRE-PRODUCTION backend certification snapshot only",
  "include": [
    {"path": "BACKEND/**/*.py", "category": "runtime", "owner": "approved backend domain owners", "purpose": "canonical backend runtime snapshot", "approval": "approved implemented increments", "dependency": "pyproject.toml and uv.lock"},
    {"path": "tests/**/*.py", "category": "test", "owner": "Engineering Governance", "purpose": "backend regression and quality evidence", "approval": "Q2 and Q3 authorization", "dependency": "BACKEND/**/*.py"},
    {"path": "database/__init__.py", "category": "migration", "owner": "Persistence Foundation", "purpose": "migration package", "approval": "approved migration governance", "dependency": "alembic.ini"},
    {"path": "database/migrate.py", "category": "migration", "owner": "Persistence Foundation", "purpose": "migration command wrapper", "approval": "approved migration governance", "dependency": "database/migrations/**"},
    {"path": "database/certify_restore.py", "category": "tooling", "owner": "Engineering Governance", "purpose": "backup and restore certification command", "approval": "AYO-RQC-1", "dependency": "approved disposable PostgreSQL environment"},
    {"path": "database/migrations/**", "category": "migration", "owner": "Persistence Foundation", "purpose": "canonical migration chain through 20260724_0056", "approval": "migration governance including corrected 0016 exception", "dependency": "alembic.ini"},
    {"path": "ayo.py", "category": "runtime", "owner": "Backend composition", "purpose": "backend entry point", "approval": "current approved backend snapshot", "dependency": "BACKEND/**"},
    {"path": "alembic.ini", "category": "migration", "owner": "Persistence Foundation", "purpose": "Alembic configuration", "approval": "approved migration governance", "dependency": "database/migrations/**"},
    {"path": "pyproject.toml", "category": "tooling", "owner": "Engineering Governance", "purpose": "authoritative quality and Python project configuration", "approval": "AYO-RQC-1 Q1", "dependency": "uv.lock"},
    {"path": "uv.lock", "category": "tooling", "owner": "Engineering Governance", "purpose": "reproducible dependency lock", "approval": "AYO-RQC-1 Q1", "dependency": "pyproject.toml"},
    {"path": ".python-version", "category": "tooling", "owner": "Engineering Governance", "purpose": "Python toolchain declaration", "approval": "AYO-RQC-1 Q1", "dependency": "pyproject.toml"},
    {"path": ".github/workflows/ci.yml", "category": "CI", "owner": "Engineering Governance", "purpose": "pinned backend certification workflow", "approval": "AYO-RQC-1 Q1", "dependency": "quality/evidence/**"},
    {"path": ".gitleaks.toml", "category": "tooling", "owner": "Engineering Governance", "purpose": "approved narrow Gitleaks exceptions", "approval": "CTO and Founder adjudication", "dependency": "Gitleaks v8.30.1"},
    {"path": ".gitignore", "category": "metadata", "owner": "Engineering Governance", "purpose": "local-output exclusion hygiene", "approval": "checkpoint governance", "dependency": "none"},
    {"path": "quality/evidence/**", "category": "evidence_definition", "owner": "Engineering Governance", "purpose": "commit-bound certification schema and template", "approval": "AYO-RQC-1 Q1", "dependency": ".github/workflows/ci.yml"},
    {"path": "README.md", "category": "metadata", "owner": "Repository Governance", "purpose": "repository entry documentation", "approval": "current approved repository snapshot", "dependency": "canonical governance documents"},
    {"path": "AGENTS.md", "category": "metadata", "owner": "Repository Governance", "purpose": "repository engineering instructions", "approval": "current repository authority", "dependency": "docs/AYO_CONSTITUTION.md"},
    {"path": "quality/backend_checkpoint_manifest.json", "category": "evidence_definition", "owner": "Engineering Governance", "purpose": "canonical checkpoint file-set contract", "approval": "this mission", "dependency": "manifest report"},
    {"path": "docs/AYO_BACKEND_CERTIFICATION_CHECKPOINT_MANIFEST_2026-07-24.md", "category": "governance", "owner": "Engineering Governance", "purpose": "manifest decision and reconstruction evidence", "approval": "this mission", "dependency": "quality/backend_checkpoint_manifest.json"}
  ],
  "documents": [
    "docs/AYO_CONSTITUTION.md",
    "docs/AYO_ARCHITECTURE.md",
    "docs/AYO_MASTER_BLUEPRINT.md",
    "docs/AYO_PLATFORM_PRINCIPLES.md",
    "docs/AYO_ROADMAP.md",
    "docs/AYO_DECISION_LOG.md",
    "docs/AYO_ENGINEERING_WORKFLOW.md",
    "docs/AYO_DATABASE_MIGRATIONS.md",
    "docs/AYO_COURIER_PICKUP_ARCHITECTURE_LAUNCH_ADMISSION_PACKAGE.md",
    "docs/ADR_COURIER_PICKUP_REFINEMENT_2026-07-24.md",
    "docs/AYO_COURIER_PICKUP_MODELS_AND_BOUNDARIES.md",
    "docs/AYO_COURIER_PICKUP_RISK_LAUNCH_SEQUENCE.md",
    "docs/AYO_COURIER_PICKUP_CTO_GATE_REPORT_2026-07-24.md",
    "docs/AYO_COURIER_PICKUP_INCREMENT_1_IMPLEMENTATION_AUTHORIZATION_2026-07-24.md",
    "docs/AYO_COURIER_PICKUP_INCREMENT_1_IMPLEMENTATION.md",
    "docs/AYO_COURIER_PICKUP_INCREMENT_1_VERIFICATION_CERTIFICATION_2026-07-24.md",
    "docs/AYO_REPOSITORY_QUALITY_CONTRACT_CTO_GATE_2026-07-24.md",
    "docs/AYO_RQC_1_CONTROL_DECISIONS_2026-07-24.md",
    "docs/AYO_REPOSITORY_QUALITY_COMMANDS.md",
    "docs/AYO_REPOSITORY_QUALITY_MARKER_REGISTRY.md",
    "docs/AYO_REPOSITORY_QUALITY_Q1_IMPLEMENTATION_AUTHORIZATION_2026-07-24.md",
    "docs/AYO_REPOSITORY_QUALITY_Q1_IMPLEMENTATION_2026-07-24.md",
    "docs/AYO_REPOSITORY_QUALITY_Q2_MYPY_REMEDIATION_2026-07-24.md",
    "docs/AYO_REPOSITORY_QUALITY_Q3_COVERAGE_REMEDIATION_2026-07-24.md",
    "docs/AYO_REPOSITORY_QUALITY_Q3_CONTINUATION_2026-07-24.md",
    "docs/AYO_REPOSITORY_QUALITY_Q3_CONTINUATION_2_2026-07-24.md",
    "docs/AYO_REPOSITORY_QUALITY_Q3_CONTINUATION_3_2026-07-24.md",
    "docs/AYO_REPOSITORY_QUALITY_Q3_COVERAGE_FEASIBILITY_2026-07-24.md",
    "docs/AYO_REPOSITORY_QUALITY_POSTGRESQL_BASELINE_PREFLIGHT_2026-07-24.md",
    "docs/AYO_REPOSITORY_QUALITY_CLEAN_CHECKPOINT_PREPARATION_2026-07-24.md",
    "docs/AYO_REPOSITORY_QUALITY_CHECKPOINT_ADJUDICATION_2026-07-24.md",
    "docs/AYO_MIGRATION_0016_PREPRODUCTION_CORRECTION_GOVERNANCE_2026-07-24.md",
    "docs/AYO_REPOSITORY_QUALITY_CHRONOLOGICAL_RECONSTRUCTION_2026-07-24.md"
  ],
  "exclude_from_dirty_snapshot": [
    "AYO-Mobile/**",
    "BIBLE/**",
    "DESIGN/**",
    "DOCUMENTS/**",
    "docs/** except the explicit documents list",
    "**/__pycache__/**",
    ".venv/**",
    ".mypy_cache/**",
    ".ruff_cache/**",
    ".pytest_cache/**",
    ".pip-audit*-cache/**",
    ".tools/**",
    ".tmp/**",
    ".coverage",
    "htmlcov/**",
    ".pytest*.txt",
    ".pytest*.xml",
    ".mypy*.txt",
    ".tmp*.json",
    ".env",
    "screenshots and device logs",
    "tests/test_ride_flow.py"
  ],
  "inherited_but_not_certified": [
    "mobile and non-backend files already present in the base commit remain untouched; no dirty-workspace version is copied or certified"
  ],
  "review_required": [],
  "open_gates": [
    "whole-BACKEND branch coverage below 70.00%",
    "PostgreSQL 17/PostGIS 3.6 execution not performed",
    "Engineering Certification incomplete"
  ]
}
